LICENSE.txt
MANIFEST.in
README.rst
setup.py
checklists/__init__.py
checklists/admin.py
checklists/autocomplete_light_registry.py
checklists/filters.py
checklists/forms.py
checklists/models.py
checklists/utils.py
checklists.egg-info/PKG-INFO
checklists.egg-info/SOURCES.txt
checklists.egg-info/dependency_links.txt
checklists.egg-info/requires.txt
checklists.egg-info/top_level.txt
checklists/api/__init__.py
checklists/api/checklist.py
checklists/api/entry.py
checklists/data/activity.csv
checklists/data/age.csv
checklists/data/direction.csv
checklists/data/plumage.csv
checklists/data/protocol.csv
checklists/data/rank.csv
checklists/data/sex.csv
checklists/data/taxonomy.csv
checklists/locale/en/LC_MESSAGES/django.po
checklists/locale/pt/LC_MESSAGES/django.po
checklists/management/__init__.py
checklists/management/commands/__init__.py
checklists/management/commands/load_checklists.py
checklists/migrations/0001_initial.py
checklists/migrations/0002_add_speciesgroup.py
checklists/migrations/0003_add_source_identifiers.py
checklists/migrations/0004_add_species_include.py
checklists/migrations/0005_set_species_include.py
checklists/migrations/0006_add_protocol.py
checklists/migrations/0007_set_protocol.py
checklists/migrations/0008_clean_protocol.py
checklists/migrations/0009_rename_detail_long.py
checklists/migrations/0010_set_detail_coordinates.py
checklists/migrations/0011_clean_coordinates.py
checklists/migrations/0012_add_types.py
checklists/migrations/0013_set_types.py
checklists/migrations/0014_clean_types.py
checklists/migrations/0015_prepare_for_constraints.py
checklists/migrations/0016_tighten_constraints.py
checklists/migrations/0017_add_delete_rules_and_rename.py
checklists/migrations/0018_rename_protocol.py
checklists/migrations/0019_rename_protocol_type.py
checklists/migrations/0020_add_code.py
checklists/migrations/0021_add_activity.py
checklists/migrations/0022_add_time.py
checklists/migrations/0023_set_method_time.py
checklists/migrations/0024_delete_checklist_time.py
checklists/migrations/0025_rename_observers.py
checklists/migrations/0026_add_many_observers_and_reporter.py
