Metadata-Version: 1.1
Name: checklists
Version: 0.4.12
Summary: A reusable Django model for managing checklists of birds.
Home-page: http://www.github.com/StuartMacKay/checklists
Author: Stuart MacKay
Author-email: smackay@flagstonesoftware.com
License: BSD
Keywords: django checklists
Platform: UNKNOWN
Classifier: Development Status :: 3 - Alpha
Classifier: Environment :: Web Environment
Classifier: Intended Audience :: Developers
Classifier: License :: OSI Approved :: BSD License
Classifier: Operating System :: OS Independent
Classifier: Programming Language :: Python
Classifier: Framework :: Django
Classifier: Natural Language :: English
